Metadata-Version: 2.1
Name: assertbr
Version: 0.0.2
Summary: Framework pra testes de API
Author: André Vieira dos Santos
Author-email: assertbr7@gmail.com
License: MIT License
Keywords: assert br
License-File: LICENSE
Requires-Dist: requests
